{
  "title": "Development planning",
  "user": "user",
  "week": "week",
  "lastWeek": "last week",
  "currentWeek": "current week",
  "nextWeek": "next week",
  "workload": "Workload",
  "availability": "Availability",
  "clonePlan": "Clone plan",
  "plan": "Plan",
  "owner": "Owner",
  "description": "Description",
  "clone": "clone",
  "editPlan": "Edit plan",
  "removePlan": "Remove plan",
  "project": "Project",
  "setting": "Setting",
  "planning": "Planning",
  "priorit": "Priorit",
  "low": "Low",
  "normal": "Normal",
  "high": "High",
  "year": "Year",
  "month": "Month",
  "assigned": "assigned",
  "created": "created",
  "close": "Close",
  "update": "Update",
  "searchUser":"search user",
  "login":"Log in",
  "email":"E-mail",
  "password":"Password",
  "signin":"Sign in",
  "createNewPlan":"Create New Plan",
  "weekOfYear":"weekOfYear",
  "submit":"Submit",
  "saveChanges":"Save Changes"
 


}
